odoo/addons/pos_screen_element_custom_size/README.rst
odoo/addons/pos_screen_element_custom_size/__init__.py
odoo/addons/pos_screen_element_custom_size/__manifest__.py
odoo/addons/pos_screen_element_custom_size/i18n/it.po
odoo/addons/pos_screen_element_custom_size/i18n/pos_screen_element_custom_size.pot
odoo/addons/pos_screen_element_custom_size/models/__init__.py
odoo/addons/pos_screen_element_custom_size/models/pos_config.py
odoo/addons/pos_screen_element_custom_size/models/res_config_settings.py
odoo/addons/pos_screen_element_custom_size/readme/CONFIGURE.md
odoo/addons/pos_screen_element_custom_size/readme/CONTEXT.md
odoo/addons/pos_screen_element_custom_size/readme/DESCRIPTION.md
odoo/addons/pos_screen_element_custom_size/readme/ROADMAP.md
odoo/addons/pos_screen_element_custom_size/readme/USAGE.md
odoo/addons/pos_screen_element_custom_size/static/description/icon.png
odoo/addons/pos_screen_element_custom_size/static/description/index.html
odoo/addons/pos_screen_element_custom_size/static/src/xml/ProductItem.xml
odoo/addons/pos_screen_element_custom_size/static/src/xml/ProductsWidget.xml
odoo/addons/pos_screen_element_custom_size/views/res_config_settings_views.xml
odoo_addon_pos_screen_element_custom_size-16.0.1.0.0.4.dist-info/METADATA
odoo_addon_pos_screen_element_custom_size-16.0.1.0.0.4.dist-info/WHEEL
odoo_addon_pos_screen_element_custom_size-16.0.1.0.0.4.dist-info/top_level.txt
odoo_addon_pos_screen_element_custom_size-16.0.1.0.0.4.dist-info/RECORD
